Metadata-Version: 2.1
Name: object3
Version: 2.7.0
Summary: Preview a GRUB 2.x theme using KVM/QEMU
Home-page: https://github.com/hartwork/object3
Author: Sebastian Pipping
Author-email: sebastian@pipping.org
License: GPL v2 or later
Download-URL: https://github.com/hartwork/object3/archive/2.7.0.tar.gz
Platform: UNKNOWN
Classifier: Development Status :: 4 - Beta
Classifier: Environment :: Console
Classifier: Intended Audience :: Developers
Classifier: Intended Audience :: End Users/Desktop
Classifier: License :: OSI Approved :: GNU General Public License v2 or later (GPLv2+)
Classifier: Natural Language :: English
Classifier: Programming Language :: Python
Classifier: Programming Language :: Python :: 3
Classifier: Programming Language :: Python :: 3.7
Classifier: Programming Language :: Python :: 3.8
Classifier: Programming Language :: Python :: 3.9
Classifier: Programming Language :: Python :: 3.10
Classifier: Programming Language :: Python :: 3 :: Only
Classifier: Topic :: System :: Boot
Classifier: Topic :: Utilities
Requires-Python: >=3.7
